naeural_client/__init__.py
naeural_client/_ver.py
naeural_client/base_decentra_object.py
naeural_client/plugins_manager_mixin.py
naeural_client/base/__init__.py
naeural_client/base/distributed_custom_code_presets.py
naeural_client/base/generic_session.py
naeural_client/base/instance.py
naeural_client/base/pipeline.py
naeural_client/base/plugin_template.py
naeural_client/base/responses.py
naeural_client/base/transaction.py
naeural_client/base/webapp_pipeline.py
naeural_client/base/payload/__init__.py
naeural_client/base/payload/payload.py
naeural_client/bc/__init__.py
naeural_client/bc/base.py
naeural_client/bc/chain.py
naeural_client/bc/ec.py
naeural_client/bc/evm.py
naeural_client/certs/__init__.py
naeural_client/certs/a0d9818f.ala.eu-central-1.emqxsl.com.crt
naeural_client/certs/r9092118.ala.eu-central-1.emqxsl.com.crt
naeural_client/certs/s624dbd4.ala.us-east-1.emqxsl.com.crt
naeural_client/cli/README.md
naeural_client/cli/cli.py
naeural_client/cli/cli_commands.py
naeural_client/cli/nodes.py
naeural_client/cli/oracles.py
naeural_client/code_cheker/__init__.py
naeural_client/code_cheker/base.py
naeural_client/code_cheker/checker.py
naeural_client/comm/__init__.py
naeural_client/comm/amqp_wrapper.py
naeural_client/comm/mqtt_wrapper.py
naeural_client/const/README.md
naeural_client/const/__init__.py
naeural_client/const/apps.py
naeural_client/const/base.py
naeural_client/const/comms.py
naeural_client/const/environment.py
naeural_client/const/evm_net.py
naeural_client/const/formatter.py
naeural_client/const/heartbeat.py
naeural_client/const/misc.py
naeural_client/const/payload.py
naeural_client/default/__init__.py
naeural_client/default/instance/__init__.py
naeural_client/default/instance/chain_dist_custom_job_01_plugin.py
naeural_client/default/instance/custom_webapi_01_plugin.py
naeural_client/default/instance/net_mon_01_plugin.py
naeural_client/default/instance/telegram_basic_bot_01_plugin.py
naeural_client/default/instance/telegram_conversational_bot_01_plugin.py
naeural_client-3.2.3.dist-info/METADATA
naeural_client-3.2.3.dist-info/WHEEL
naeural_client-3.2.3.dist-info/entry_points.txt
naeural_client-3.2.3.dist-info/licenses/LICENSE
naeural_client-3.2.3.dist-info/RECORD
