Metadata-Version: 2.4
Name: naeural_client
Version: 3.2.3
Summary: `naeural_client` is the Python SDK required for client app development for the Naeural Edge Protocol Edge Protocol framework
Project-URL: Homepage, https://github.com/NaeuralEdgeProtocol/naeural_client
Project-URL: Bug Tracker, https://github.com/NaeuralEdgeProtocol/naeural_client/issues
Author-email: Andrei Ionut Damian <andrei.damian@me.com>, Cristan Bleotiu <cristibleotiu@gmail.com>, Stefan Saraev <saraevstefan@gmail.com>
License-File: LICENSE
Classifier: License :: OSI Approved :: MIT License
Classifier: Operating System :: OS Independent
Classifier: Programming Language :: Python :: 3
Requires-Python: >=3.8
Requires-Dist: cryptography>=39.0.0
Requires-Dist: numpy
Requires-Dist: paho-mqtt
Requires-Dist: pandas
Requires-Dist: pika
Requires-Dist: pyaml
Requires-Dist: pyopenssl>=23.0.0
Requires-Dist: python-dateutil
Requires-Dist: web3
